cmdrdata_anthropic/__init__.py
cmdrdata_anthropic/async_client.py
cmdrdata_anthropic/client.py
cmdrdata_anthropic/context.py
cmdrdata_anthropic/exceptions.py
cmdrdata_anthropic/logging_config.py
cmdrdata_anthropic/performance.py
cmdrdata_anthropic/proxy.py
cmdrdata_anthropic/retry.py
cmdrdata_anthropic/security.py
cmdrdata_anthropic/tracker.py
cmdrdata_anthropic/validation.py
cmdrdata_anthropic/version_compat.py
cmdrdata_anthropic-0.2.0.dist-info/METADATA
cmdrdata_anthropic-0.2.0.dist-info/WHEEL
cmdrdata_anthropic-0.2.0.dist-info/RECORD
