Metadata-Version: 2.4
Name: cmdrdata-anthropic
Version: 0.2.0
Summary: Customer tracking and usage-based billing for Anthropic Claude with arbitrary metadata support
Project-URL: Homepage, https://github.com/cmdrdata-ai/cmdrdata-anthropic
Project-URL: Documentation, https://docs.cmdrdata.ai/anthropic
Project-URL: Repository, https://github.com/cmdrdata-ai/cmdrdata-anthropic
Project-URL: Bug Tracker, https://github.com/cmdrdata-ai/cmdrdata-anthropic/issues
Author-email: CMDR Data Team <team@cmdrdata.ai>
License: MIT
Keywords: ai,anthropic,api-wrapper,claude,customer-tracking,fine-grained-billing,llm,metadata,usage-based-billing
Classifier: Development Status :: 4 - Beta
Classifier: Intended Audience :: Developers
Classifier: License :: OSI Approved :: MIT License
Classifier: Operating System :: OS Independent
Classifier: Programming Language :: Python :: 3
Classifier: Programming Language :: Python :: 3.9
Classifier: Programming Language :: Python :: 3.10
Classifier: Programming Language :: Python :: 3.11
Classifier: Programming Language :: Python :: 3.12
Classifier: Programming Language :: Python :: 3.13
Classifier: Topic :: Scientific/Engineering :: Artificial Intelligence
Classifier: Topic :: Software Development :: Libraries :: Python Modules
Requires-Python: >=3.9
Requires-Dist: anthropic<1.0.0,>=0.21.0
Requires-Dist: httpx>=0.24.0
Requires-Dist: packaging>=21.0
Requires-Dist: pydantic>=2.0.0
Provides-Extra: dev
Requires-Dist: black>=23.0.0; extra == 'dev'
Requires-Dist: isort>=5.12.0; extra == 'dev'
Requires-Dist: mypy>=1.0.0; extra == 'dev'
Requires-Dist: pre-commit>=3.0.0; extra == 'dev'
Requires-Dist: pytest-asyncio>=0.21.0; extra == 'dev'
Requires-Dist: pytest-cov>=4.0.0; extra == 'dev'
Requires-Dist: pytest-mock>=3.10.0; extra == 'dev'
Requires-Dist: pytest>=7.0.0; extra == 'dev'
